Metadata-Version: 2.4
Name: saturation-analysis
Version: 1.0.1
Summary: 服务区饱和度分析系统 - 流量分析、饱和度计算和预测
Author: 服务区饱和度分析系统开发团队
Author-email: dev@example.com
Keywords: saturation,analysis,traffic,highway,service area
Classifier: Development Status :: 4 - Beta
Classifier: Intended Audience :: Science/Research
Classifier: Topic :: Scientific/Engineering :: Information Analysis
Classifier: Programming Language :: Python :: 3
Classifier: Programming Language :: Python :: 3.7
Classifier: Programming Language :: Python :: 3.8
Classifier: Programming Language :: Python :: 3.9
Classifier: License :: OSI Approved :: MIT License
Classifier: Operating System :: OS Independent
Requires-Python: >=3.7
Requires-Dist: numpy>=1.19.0
Requires-Dist: pandas>=1.1.0
Requires-Dist: matplotlib>=3.3.0
Requires-Dist: scikit-learn>=0.23.0
Requires-Dist: tensorflow>=2.3.0
Requires-Dist: keras>=2.4.0
Requires-Dist: scikit-fuzzy>=0.4.2
Requires-Dist: scipy>=1.5.0
Requires-Dist: scikit-opt>=0.6.0
Requires-Dist: seaborn>=0.11.0
Requires-Dist: packaging>=20.0
Requires-Dist: openpyxl>=3.0.0
Dynamic: author
Dynamic: author-email
Dynamic: classifier
Dynamic: description
Dynamic: description-content-type
Dynamic: keywords
Dynamic: requires-dist
Dynamic: requires-python
Dynamic: summary
